db_json/__init__.py
db_json/__main__.py
db_json/cli.py
db_json/core.py
db_json/data_structures.py
db_json/server.py
db.json-0.1.0.dist-info/LICENSE
db.json-0.1.0.dist-info/WHEEL
db.json-0.1.0.dist-info/METADATA
db.json-0.1.0.dist-info/RECORD
