Metadata-Version: 2.1
Name: db.json
Version: 0.1.0
Summary: 
Author: Andrii Maksymov
Author-email: maximov.echo@gmail.com
Requires-Python: >=3.7,<4.0
Classifier: Programming Language :: Python :: 3
Classifier: Programming Language :: Python :: 3.7
Classifier: Programming Language :: Python :: 3.8
Requires-Dist: pydantic (>=1.7,<2.0)
Requires-Dist: starlette (>=0.13.8,<0.14.0)
Requires-Dist: typer (>=0.3.2,<0.4.0)
Requires-Dist: uvicorn (>=0.12.2,<0.13.0)
